linkparser/__init__.py
linkparser/function.py
linkparser/linkparser.py
linkparser-1.0.dist-info/LICENSE
linkparser-1.0.dist-info/METADATA
linkparser-1.0.dist-info/WHEEL
linkparser-1.0.dist-info/entry_points.txt
linkparser-1.0.dist-info/top_level.txt
linkparser-1.0.dist-info/RECORD
