Metadata-Version: 2.1
Name: linkparser
Version: 1.0
Summary: A Simple Python Package to Extract All Links from a Target Domain or URL.
Home-page: https://github.com/thehackersbrain/linkparser
Author: Gaurav Raj
Author-email: techw803@gmail.com
License: MIT
Keywords: linkparser,thehackersbrain,hacking,web scraping,python,python3
Platform: UNKNOWN
Requires-Dist: requests
Requires-Dist: rich
Requires-Dist: pyfiglet
Requires-Dist: bs4
